odoo8_addon_event_multi_image-8.0.1.0.0-py2.7-nspkg.pth
odoo_addons/event_multi_image/__openerp__.py
odoo_addons/event_multi_image/__init__.py
odoo_addons/event_multi_image/README.rst
odoo_addons/event_multi_image/models/__init__.py
odoo_addons/event_multi_image/models/event.py
odoo_addons/event_multi_image/views/event_view.xml
odoo_addons/event_multi_image/images/images.png
odoo_addons/event_multi_image/static/description/icon.svg
odoo_addons/event_multi_image/static/description/icon.png
odoo8_addon_event_multi_image-8.0.1.0.0.dist-info/top_level.txt
odoo8_addon_event_multi_image-8.0.1.0.0.dist-info/WHEEL
odoo8_addon_event_multi_image-8.0.1.0.0.dist-info/RECORD
odoo8_addon_event_multi_image-8.0.1.0.0.dist-info/metadata.json
odoo8_addon_event_multi_image-8.0.1.0.0.dist-info/DESCRIPTION.rst
odoo8_addon_event_multi_image-8.0.1.0.0.dist-info/METADATA
odoo8_addon_event_multi_image-8.0.1.0.0.dist-info/namespace_packages.txt
